{
	"ilk_station_kushehr": {
		"defaultName": "Kushehr Orbital Yards",
		"defaultRadius": 80,
		"customDescriptionId": "ilk_station_kushehr",
		"interactionImage": "graphics/ilk/illustrations/interdiction.png",
		"icon": "graphics/icons/station0.png",
		"iconWidth": 24,
		"iconHeight": 24,
		"sprite": "graphics/ilk/stations/kushehr.png",
		"spriteWidth": 96,
		"spriteHeight": 38.66,
		"renderShadow": false,
		"useLightColor": true,
		"showInCampaign": true,
		"showIconOnMap": true,
		"showNameOnMap": false,
		"scaleNameWithZoom": false,
		"tags": [
			"station"
		],
		"layers": [
			"STATIONS"
		]
	}
}
